fmplib/unit8.cpython-311-x86_64-linux-musl.so
fmplib/unit7.cpython-311-x86_64-linux-musl.so
fmplib/unit6.cpython-311-x86_64-linux-musl.so
fmplib/unit2.cpython-311-x86_64-linux-musl.so
fmplib/util.py
fmplib/pyqueue.py
fmplib/__init__.py
fmplib/unit9.cpython-311-x86_64-linux-musl.so
fmplib/unit1.cpython-311-x86_64-linux-musl.so
fmplib/unit5.cpython-311-x86_64-linux-musl.so
fmplib/unit3.cpython-311-x86_64-linux-musl.so
fmplib/unit4.cpython-311-x86_64-linux-musl.so
mit_21m387-1.0.7.dist-info/top_level.txt
mit_21m387-1.0.7.dist-info/RECORD
mit_21m387-1.0.7.dist-info/LICENSE.md
mit_21m387-1.0.7.dist-info/METADATA
mit_21m387-1.0.7.dist-info/WHEEL
