Metadata-Version: 2.1
Name: mit-21m387
Version: 1.0.7
Summary: "Python package for MIT's 21M.387"
Author: Eran Egozy
Requires-Python: ~=3.11.1
License-File: LICENSE.md
